datafaker_ai/__init__.py
datafaker_ai/edge_case_handler.py
datafaker_ai/formatter.py
datafaker_ai/generator.py
datafaker_ai/prompts.py
datafaker_ai/utils.py
faker_ai-0.2.1.dist-info/METADATA
faker_ai-0.2.1.dist-info/WHEEL
faker_ai-0.2.1.dist-info/top_level.txt
faker_ai-0.2.1.dist-info/RECORD
